_vec64.cpython-310-aarch64-linux-gnu.so
vec64-0.0.7.dist-info/LICENSE
vec64-0.0.7.dist-info/WHEEL
vec64-0.0.7.dist-info/top_level.txt
vec64-0.0.7.dist-info/RECORD
vec64-0.0.7.dist-info/METADATA
vec64/__init__.py
vec64/wrappers.py
vec64/span.py
vec64/util.py
vec64/ctype.py
