Metadata-Version: 2.1
Name: vec64
Version: 0.0.7
Summary: C extension functions to make DOM tokenizers faster
Author-email: Gary Benson <gary@gbenson.net>
Project-URL: Homepage, https://github.com/gbenson/vec64
Project-URL: Source, https://github.com/gbenson/vec64
Classifier: Development Status :: 4 - Beta
Classifier: Intended Audience :: Developers
Classifier: Intended Audience :: Science/Research
Classifier: License :: OSI Approved :: Apache Software License
Classifier: Operating System :: OS Independent
Classifier: Programming Language :: Python :: 3
Classifier: Topic :: Scientific/Engineering :: Artificial Intelligence
Classifier: Topic :: Scientific/Engineering :: Information Analysis
Requires-Python: >=3.10
License-File: LICENSE
Provides-Extra: dev
Requires-Dist: flake8 ; extra == 'dev'
Requires-Dist: pytest ; extra == 'dev'
